<?xml version="1.0" encoding="utf-8"?>
<abapGit version="v1.0.0" serializer="LCL_OBJECT_SPRX" serializer_version="v1.0.0">
 <asx:abap xmlns:asx="http://www.sap.com/abapxml" version="1.0">
  <asx:values>
   <PROXY_HEADER>
    <item>
     <OBJECT>TABL</OBJECT>
     <OBJ_NAME>ZEBIZ_CHARGECUSTOMER</OBJ_NAME>
     <OBJECT_M>TABL</OBJECT_M>
     <OBJ_NAME_M>ZEBIZ_CHARGECUSTOMER</OBJ_NAME_M>
     <HASH_ID>C4EBC6FFE012367A1565BD24A49CFBD0188A680C</HASH_ID>
     <ID>&lt;type&gt; Customer http://eBizCharge.ServiceModel.SOAP http://eBizCharge.ServiceModel.SOAP</ID>
     <IFR_GLOBAL>X</IFR_GLOBAL>
     <IFR_TYPE>type</IFR_TYPE>
     <IFR_NAME>Customer</IFR_NAME>
     <IFR_NSPCE>http://eBizCharge.ServiceModel.SOAP</IFR_NSPCE>
     <IFR_GNSPCE>http://eBizCharge.ServiceModel.SOAP</IFR_GNSPCE>
     <GEN_VERS>0005</GEN_VERS>
     <PREFIX>ZEBIZ_CHARGE</PREFIX>
     <CATEGORY>ifmtypedef</CATEGORY>
     <GEN_APPL>WEBSERVICES</GEN_APPL>
     <X-ML_NSPCE>http://eBizCharge.ServiceModel.SOAP</X-ML_NSPCE>
     <X-ML_NAME>Customer</X-ML_NAME>
    </item>
   </PROXY_HEADER>
   <PROXY_DATA>
    <item>
     <OBJECT>TABL</OBJECT>
     <OBJ_NAME>ZEBIZ_CHARGECUSTOMER</OBJ_NAME>
     <OBJECT1>FIEL</OBJECT1>
     <OBJ_NAME1>BILLING_ADDRESS</OBJ_NAME1>
     <OBJECT2>FIEL</OBJECT2>
     <OBJ_NAME2>BILLING_ADDRESS</OBJ_NAME2>
     <OBJECT_R>TABL</OBJECT_R>
     <OBJ_NAME_R>ZEBIZ_CHARGEADDRESS</OBJ_NAME_R>
     <ID>&lt;element&gt; {http://eBizCharge.ServiceModel.SOAP}BillingAddress &lt;type&gt; Customer http://eBizCharge.ServiceModel.SOAP http://eBizCharge.ServiceModel.SOAP</ID>
     <IFR_TYPE>element</IFR_TYPE>
     <IFR_NAME>BillingAddress</IFR_NAME>
     <IFR_TAGTYP>E</IFR_TAGTYP>
     <IFR_MAXOCC>1</IFR_MAXOCC>
     <IFR_OPTNL>X</IFR_OPTNL>
     <IFR_QUALIF>X</IFR_QUALIF>
     <IFR_SCALE>-2</IFR_SCALE>
     <R3_TYPE>FIEL</R3_TYPE>
     <R3_NAME>BILLING_ADDRESS</R3_NAME>
     <R3_SEQNUM>000013</R3_SEQNUM>
    </item>
    <item>
     <OBJECT>TABL</OBJECT>
     <OBJ_NAME>ZEBIZ_CHARGECUSTOMER</OBJ_NAME>
     <OBJECT1>FIEL</OBJECT1>
     <OBJ_NAME1>CELL_PHONE</OBJ_NAME1>
     <OBJECT2>FIEL</OBJECT2>
     <OBJ_NAME2>CELL_PHONE</OBJ_NAME2>
     <ID>&lt;element&gt; {http://eBizCharge.ServiceModel.SOAP}CellPhone &lt;type&gt; Customer http://eBizCharge.ServiceModel.SOAP http://eBizCharge.ServiceModel.SOAP</ID>
     <IFR_TYPE>element</IFR_TYPE>
     <IFR_NAME>CellPhone</IFR_NAME>
     <IFR_TAGTYP>E</IFR_TAGTYP>
     <IFR_MAXOCC>1</IFR_MAXOCC>
     <IFR_OPTNL>X</IFR_OPTNL>
     <IFR_QUALIF>X</IFR_QUALIF>
     <IFR_XSDTYP>string</IFR_XSDTYP>
     <IFR_SCALE>-2</IFR_SCALE>
     <R3_TYPE>FIEL</R3_TYPE>
     <R3_NAME>CELL_PHONE</R3_NAME>
     <R3_DATATYP>STRG</R3_DATATYP>
     <R3_SEQNUM>000008</R3_SEQNUM>
    </item>
    <item>
     <OBJECT>TABL</OBJECT>
     <OBJ_NAME>ZEBIZ_CHARGECUSTOMER</OBJ_NAME>
     <OBJECT1>FIEL</OBJECT1>
     <OBJ_NAME1>COMPANY_NAME</OBJ_NAME1>
     <OBJECT2>FIEL</OBJECT2>
     <OBJ_NAME2>COMPANY_NAME</OBJ_NAME2>
     <ID>&lt;element&gt; {http://eBizCharge.ServiceModel.SOAP}CompanyName &lt;type&gt; Customer http://eBizCharge.ServiceModel.SOAP http://eBizCharge.ServiceModel.SOAP</ID>
     <IFR_TYPE>element</IFR_TYPE>
     <IFR_NAME>CompanyName</IFR_NAME>
     <IFR_TAGTYP>E</IFR_TAGTYP>
     <IFR_MAXOCC>1</IFR_MAXOCC>
     <IFR_OPTNL>X</IFR_OPTNL>
     <IFR_QUALIF>X</IFR_QUALIF>
     <IFR_XSDTYP>string</IFR_XSDTYP>
     <IFR_SCALE>-2</IFR_SCALE>
     <R3_TYPE>FIEL</R3_TYPE>
     <R3_NAME>COMPANY_NAME</R3_NAME>
     <R3_DATATYP>STRG</R3_DATATYP>
     <R3_SEQNUM>000006</R3_SEQNUM>
    </item>
    <item>
     <OBJECT>TABL</OBJECT>
     <OBJ_NAME>ZEBIZ_CHARGECUSTOMER</OBJ_NAME>
     <OBJECT1>FIEL</OBJECT1>
     <OBJ_NAME1>CUSTOMER_CUSTOM_FIELDS</OBJ_NAME1>
     <OBJECT2>FIEL</OBJECT2>
     <OBJ_NAME2>CUSTOMER_CUSTOM_FIELDS</OBJ_NAME2>
     <OBJECT_R>TABL</OBJECT_R>
     <OBJ_NAME_R>ZEBIZ_CHARGEARRAY_OF_EBIZ_CUST</OBJ_NAME_R>
     <ID>&lt;element&gt; {http://eBizCharge.ServiceModel.SOAP}CustomerCustomFields &lt;type&gt; Customer http://eBizCharge.ServiceModel.SOAP http://eBizCharge.ServiceModel.SOAP</ID>
     <IFR_TYPE>element</IFR_TYPE>
     <IFR_NAME>CustomerCustomFields</IFR_NAME>
     <IFR_TAGTYP>E</IFR_TAGTYP>
     <IFR_MAXOCC>1</IFR_MAXOCC>
     <IFR_OPTNL>X</IFR_OPTNL>
     <IFR_QUALIF>X</IFR_QUALIF>
     <IFR_SCALE>-2</IFR_SCALE>
     <R3_TYPE>FIEL</R3_TYPE>
     <R3_NAME>CUSTOMER_CUSTOM_FIELDS</R3_NAME>
     <R3_SEQNUM>000019</R3_SEQNUM>
    </item>
    <item>
     <OBJECT>TABL</OBJECT>
     <OBJ_NAME>ZEBIZ_CHARGECUSTOMER</OBJ_NAME>
     <OBJECT1>FIEL</OBJECT1>
     <OBJ_NAME1>CUSTOMER_ID</OBJ_NAME1>
     <OBJECT2>FIEL</OBJECT2>
     <OBJ_NAME2>CUSTOMER_ID</OBJ_NAME2>
     <ID>&lt;element&gt; {http://eBizCharge.ServiceModel.SOAP}CustomerId &lt;type&gt; Customer http://eBizCharge.ServiceModel.SOAP http://eBizCharge.ServiceModel.SOAP</ID>
     <IFR_TYPE>element</IFR_TYPE>
     <IFR_NAME>CustomerId</IFR_NAME>
     <IFR_TAGTYP>E</IFR_TAGTYP>
     <IFR_MAXOCC>1</IFR_MAXOCC>
     <IFR_OPTNL>X</IFR_OPTNL>
     <IFR_QUALIF>X</IFR_QUALIF>
     <IFR_XSDTYP>string</IFR_XSDTYP>
     <IFR_SCALE>-2</IFR_SCALE>
     <R3_TYPE>FIEL</R3_TYPE>
     <R3_NAME>CUSTOMER_ID</R3_NAME>
     <R3_DATATYP>STRG</R3_DATATYP>
     <R3_SEQNUM>000003</R3_SEQNUM>
    </item>
    <item>
     <OBJECT>TABL</OBJECT>
     <OBJ_NAME>ZEBIZ_CHARGECUSTOMER</OBJ_NAME>
     <OBJECT1>FIEL</OBJECT1>
     <OBJ_NAME1>CUSTOMER_INTERNAL_ID</OBJ_NAME1>
     <OBJECT2>FIEL</OBJECT2>
     <OBJ_NAME2>CUSTOMER_INTERNAL_ID</OBJ_NAME2>
     <ID>&lt;element&gt; {http://eBizCharge.ServiceModel.SOAP}CustomerInternalId &lt;type&gt; Customer http://eBizCharge.ServiceModel.SOAP http://eBizCharge.ServiceModel.SOAP</ID>
     <IFR_TYPE>element</IFR_TYPE>
     <IFR_NAME>CustomerInternalId</IFR_NAME>
     <IFR_TAGTYP>E</IFR_TAGTYP>
     <IFR_MAXOCC>1</IFR_MAXOCC>
     <IFR_OPTNL>X</IFR_OPTNL>
     <IFR_QUALIF>X</IFR_QUALIF>
     <IFR_XSDTYP>string</IFR_XSDTYP>
     <IFR_SCALE>-2</IFR_SCALE>
     <R3_TYPE>FIEL</R3_TYPE>
     <R3_NAME>CUSTOMER_INTERNAL_ID</R3_NAME>
     <R3_DATATYP>STRG</R3_DATATYP>
     <R3_SEQNUM>000002</R3_SEQNUM>
    </item>
    <item>
     <OBJECT>TABL</OBJECT>
     <OBJ_NAME>ZEBIZ_CHARGECUSTOMER</OBJ_NAME>
     <OBJECT1>FIEL</OBJECT1>
     <OBJ_NAME1>CUSTOMER_LAST_SYNC_DATE_TIME</OBJ_NAME1>
     <OBJECT2>FIEL</OBJECT2>
     <OBJ_NAME2>CUSTOMER_LAST_SYNC_DATE_TIME</OBJ_NAME2>
     <ID>&lt;element&gt; {http://eBizCharge.ServiceModel.SOAP}CustomerLastSyncDateTime &lt;type&gt; Customer http://eBizCharge.ServiceModel.SOAP http://eBizCharge.ServiceModel.SOAP</ID>
     <IFR_TYPE>element</IFR_TYPE>
     <IFR_NAME>CustomerLastSyncDateTime</IFR_NAME>
     <IFR_TAGTYP>E</IFR_TAGTYP>
     <IFR_MAXOCC>1</IFR_MAXOCC>
     <IFR_OPTNL>X</IFR_OPTNL>
     <IFR_QUALIF>X</IFR_QUALIF>
     <IFR_XSDTYP>string</IFR_XSDTYP>
     <IFR_SCALE>-2</IFR_SCALE>
     <R3_TYPE>FIEL</R3_TYPE>
     <R3_NAME>CUSTOMER_LAST_SYNC_DATE_TIME</R3_NAME>
     <R3_DATATYP>STRG</R3_DATATYP>
     <R3_SEQNUM>000020</R3_SEQNUM>
    </item>
    <item>
     <OBJECT>TABL</OBJECT>
     <OBJ_NAME>ZEBIZ_CHARGECUSTOMER</OBJ_NAME>
     <OBJECT1>FIEL</OBJECT1>
     <OBJ_NAME1>CUSTOMER_NOTES</OBJ_NAME1>
     <OBJECT2>FIEL</OBJECT2>
     <OBJ_NAME2>CUSTOMER_NOTES</OBJ_NAME2>
     <ID>&lt;element&gt; {http://eBizCharge.ServiceModel.SOAP}CustomerNotes &lt;type&gt; Customer http://eBizCharge.ServiceModel.SOAP http://eBizCharge.ServiceModel.SOAP</ID>
     <IFR_TYPE>element</IFR_TYPE>
     <IFR_NAME>CustomerNotes</IFR_NAME>
     <IFR_TAGTYP>E</IFR_TAGTYP>
     <IFR_MAXOCC>1</IFR_MAXOCC>
     <IFR_OPTNL>X</IFR_OPTNL>
     <IFR_QUALIF>X</IFR_QUALIF>
     <IFR_XSDTYP>string</IFR_XSDTYP>
     <IFR_SCALE>-2</IFR_SCALE>
     <R3_TYPE>FIEL</R3_TYPE>
     <R3_NAME>CUSTOMER_NOTES</R3_NAME>
     <R3_DATATYP>STRG</R3_DATATYP>
     <R3_SEQNUM>000017</R3_SEQNUM>
    </item>
    <item>
     <OBJECT>TABL</OBJECT>
     <OBJ_NAME>ZEBIZ_CHARGECUSTOMER</OBJ_NAME>
     <OBJECT1>FIEL</OBJECT1>
     <OBJ_NAME1>CUSTOMER_TOKEN</OBJ_NAME1>
     <OBJECT2>FIEL</OBJECT2>
     <OBJ_NAME2>CUSTOMER_TOKEN</OBJ_NAME2>
     <ID>&lt;element&gt; {http://eBizCharge.ServiceModel.SOAP}CustomerToken &lt;type&gt; Customer http://eBizCharge.ServiceModel.SOAP http://eBizCharge.ServiceModel.SOAP</ID>
     <IFR_TYPE>element</IFR_TYPE>
     <IFR_NAME>CustomerToken</IFR_NAME>
     <IFR_TAGTYP>E</IFR_TAGTYP>
     <IFR_MAXOCC>1</IFR_MAXOCC>
     <IFR_OPTNL>X</IFR_OPTNL>
     <IFR_QUALIF>X</IFR_QUALIF>
     <IFR_XSDTYP>string</IFR_XSDTYP>
     <IFR_SCALE>-2</IFR_SCALE>
     <R3_TYPE>FIEL</R3_TYPE>
     <R3_NAME>CUSTOMER_TOKEN</R3_NAME>
     <R3_DATATYP>STRG</R3_DATATYP>
     <R3_SEQNUM>000016</R3_SEQNUM>
    </item>
    <item>
     <OBJECT>TABL</OBJECT>
     <OBJ_NAME>ZEBIZ_CHARGECUSTOMER</OBJ_NAME>
     <OBJECT1>FIEL</OBJECT1>
     <OBJ_NAME1>DIVISION_ID</OBJ_NAME1>
     <OBJECT2>FIEL</OBJECT2>
     <OBJ_NAME2>DIVISION_ID</OBJ_NAME2>
     <ID>&lt;element&gt; {http://eBizCharge.ServiceModel.SOAP}DivisionId &lt;type&gt; Customer http://eBizCharge.ServiceModel.SOAP http://eBizCharge.ServiceModel.SOAP</ID>
     <IFR_TYPE>element</IFR_TYPE>
     <IFR_NAME>DivisionId</IFR_NAME>
     <IFR_TAGTYP>E</IFR_TAGTYP>
     <IFR_MAXOCC>1</IFR_MAXOCC>
     <IFR_OPTNL>X</IFR_OPTNL>
     <IFR_QUALIF>X</IFR_QUALIF>
     <IFR_XSDTYP>string</IFR_XSDTYP>
     <IFR_SCALE>-2</IFR_SCALE>
     <R3_TYPE>FIEL</R3_TYPE>
     <R3_NAME>DIVISION_ID</R3_NAME>
     <R3_DATATYP>STRG</R3_DATATYP>
     <R3_SEQNUM>000021</R3_SEQNUM>
    </item>
    <item>
     <OBJECT>TABL</OBJECT>
     <OBJ_NAME>ZEBIZ_CHARGECUSTOMER</OBJ_NAME>
     <OBJECT1>FIEL</OBJECT1>
     <OBJ_NAME1>EMAIL</OBJ_NAME1>
     <OBJECT2>FIEL</OBJECT2>
     <OBJ_NAME2>EMAIL</OBJ_NAME2>
     <ID>&lt;element&gt; {http://eBizCharge.ServiceModel.SOAP}Email &lt;type&gt; Customer http://eBizCharge.ServiceModel.SOAP http://eBizCharge.ServiceModel.SOAP</ID>
     <IFR_TYPE>element</IFR_TYPE>
     <IFR_NAME>Email</IFR_NAME>
     <IFR_TAGTYP>E</IFR_TAGTYP>
     <IFR_MAXOCC>1</IFR_MAXOCC>
     <IFR_OPTNL>X</IFR_OPTNL>
     <IFR_QUALIF>X</IFR_QUALIF>
     <IFR_XSDTYP>string</IFR_XSDTYP>
     <IFR_SCALE>-2</IFR_SCALE>
     <R3_TYPE>FIEL</R3_TYPE>
     <R3_NAME>EMAIL</R3_NAME>
     <R3_DATATYP>STRG</R3_DATATYP>
     <R3_SEQNUM>000010</R3_SEQNUM>
    </item>
    <item>
     <OBJECT>TABL</OBJECT>
     <OBJ_NAME>ZEBIZ_CHARGECUSTOMER</OBJ_NAME>
     <OBJECT1>FIEL</OBJECT1>
     <OBJ_NAME1>FAX</OBJ_NAME1>
     <OBJECT2>FIEL</OBJECT2>
     <OBJ_NAME2>FAX</OBJ_NAME2>
     <ID>&lt;element&gt; {http://eBizCharge.ServiceModel.SOAP}Fax &lt;type&gt; Customer http://eBizCharge.ServiceModel.SOAP http://eBizCharge.ServiceModel.SOAP</ID>
     <IFR_TYPE>element</IFR_TYPE>
     <IFR_NAME>Fax</IFR_NAME>
     <IFR_TAGTYP>E</IFR_TAGTYP>
     <IFR_MAXOCC>1</IFR_MAXOCC>
     <IFR_OPTNL>X</IFR_OPTNL>
     <IFR_QUALIF>X</IFR_QUALIF>
     <IFR_XSDTYP>string</IFR_XSDTYP>
     <IFR_SCALE>-2</IFR_SCALE>
     <R3_TYPE>FIEL</R3_TYPE>
     <R3_NAME>FAX</R3_NAME>
     <R3_DATATYP>STRG</R3_DATATYP>
     <R3_SEQNUM>000009</R3_SEQNUM>
    </item>
    <item>
     <OBJECT>TABL</OBJECT>
     <OBJ_NAME>ZEBIZ_CHARGECUSTOMER</OBJ_NAME>
     <OBJECT1>FIEL</OBJECT1>
     <OBJ_NAME1>FIRST_NAME</OBJ_NAME1>
     <OBJECT2>FIEL</OBJECT2>
     <OBJ_NAME2>FIRST_NAME</OBJ_NAME2>
     <ID>&lt;element&gt; {http://eBizCharge.ServiceModel.SOAP}FirstName &lt;type&gt; Customer http://eBizCharge.ServiceModel.SOAP http://eBizCharge.ServiceModel.SOAP</ID>
     <IFR_TYPE>element</IFR_TYPE>
     <IFR_NAME>FirstName</IFR_NAME>
     <IFR_TAGTYP>E</IFR_TAGTYP>
     <IFR_MAXOCC>1</IFR_MAXOCC>
     <IFR_OPTNL>X</IFR_OPTNL>
     <IFR_QUALIF>X</IFR_QUALIF>
     <IFR_XSDTYP>string</IFR_XSDTYP>
     <IFR_SCALE>-2</IFR_SCALE>
     <R3_TYPE>FIEL</R3_TYPE>
     <R3_NAME>FIRST_NAME</R3_NAME>
     <R3_DATATYP>STRG</R3_DATATYP>
     <R3_SEQNUM>000004</R3_SEQNUM>
    </item>
    <item>
     <OBJECT>TABL</OBJECT>
     <OBJ_NAME>ZEBIZ_CHARGECUSTOMER</OBJ_NAME>
     <OBJECT1>FIEL</OBJECT1>
     <OBJ_NAME1>LAST_NAME</OBJ_NAME1>
     <OBJECT2>FIEL</OBJECT2>
     <OBJ_NAME2>LAST_NAME</OBJ_NAME2>
     <ID>&lt;element&gt; {http://eBizCharge.ServiceModel.SOAP}LastName &lt;type&gt; Customer http://eBizCharge.ServiceModel.SOAP http://eBizCharge.ServiceModel.SOAP</ID>
     <IFR_TYPE>element</IFR_TYPE>
     <IFR_NAME>LastName</IFR_NAME>
     <IFR_TAGTYP>E</IFR_TAGTYP>
     <IFR_MAXOCC>1</IFR_MAXOCC>
     <IFR_OPTNL>X</IFR_OPTNL>
     <IFR_QUALIF>X</IFR_QUALIF>
     <IFR_XSDTYP>string</IFR_XSDTYP>
     <IFR_SCALE>-2</IFR_SCALE>
     <R3_TYPE>FIEL</R3_TYPE>
     <R3_NAME>LAST_NAME</R3_NAME>
     <R3_DATATYP>STRG</R3_DATATYP>
     <R3_SEQNUM>000005</R3_SEQNUM>
    </item>
    <item>
     <OBJECT>TABL</OBJECT>
     <OBJ_NAME>ZEBIZ_CHARGECUSTOMER</OBJ_NAME>
     <OBJECT1>FIEL</OBJECT1>
     <OBJ_NAME1>MERCHANT_ID</OBJ_NAME1>
     <OBJECT2>FIEL</OBJECT2>
     <OBJ_NAME2>MERCHANT_ID</OBJ_NAME2>
     <ID>&lt;element&gt; {http://eBizCharge.ServiceModel.SOAP}MerchantId &lt;type&gt; Customer http://eBizCharge.ServiceModel.SOAP http://eBizCharge.ServiceModel.SOAP</ID>
     <IFR_TYPE>element</IFR_TYPE>
     <IFR_NAME>MerchantId</IFR_NAME>
     <IFR_TAGTYP>E</IFR_TAGTYP>
     <IFR_MAXOCC>1</IFR_MAXOCC>
     <IFR_OPTNL>X</IFR_OPTNL>
     <IFR_QUALIF>X</IFR_QUALIF>
     <IFR_XSDTYP>string</IFR_XSDTYP>
     <IFR_SCALE>-2</IFR_SCALE>
     <R3_TYPE>FIEL</R3_TYPE>
     <R3_NAME>MERCHANT_ID</R3_NAME>
     <R3_DATATYP>STRG</R3_DATATYP>
     <R3_SEQNUM>000001</R3_SEQNUM>
    </item>
    <item>
     <OBJECT>TABL</OBJECT>
     <OBJ_NAME>ZEBIZ_CHARGECUSTOMER</OBJ_NAME>
     <OBJECT1>FIEL</OBJECT1>
     <OBJ_NAME1>PAYMENT_METHOD_PROFILES</OBJ_NAME1>
     <OBJECT2>FIEL</OBJECT2>
     <OBJ_NAME2>PAYMENT_METHOD_PROFILES</OBJ_NAME2>
     <OBJECT_R>TABL</OBJECT_R>
     <OBJ_NAME_R>ZEBIZ_CHARGEARRAY_OF_PAYMENT_M</OBJ_NAME_R>
     <ID>&lt;element&gt; {http://eBizCharge.ServiceModel.SOAP}PaymentMethodProfiles &lt;type&gt; Customer http://eBizCharge.ServiceModel.SOAP http://eBizCharge.ServiceModel.SOAP</ID>
     <IFR_TYPE>element</IFR_TYPE>
     <IFR_NAME>PaymentMethodProfiles</IFR_NAME>
     <IFR_TAGTYP>E</IFR_TAGTYP>
     <IFR_MAXOCC>1</IFR_MAXOCC>
     <IFR_OPTNL>X</IFR_OPTNL>
     <IFR_QUALIF>X</IFR_QUALIF>
     <IFR_SCALE>-2</IFR_SCALE>
     <R3_TYPE>FIEL</R3_TYPE>
     <R3_NAME>PAYMENT_METHOD_PROFILES</R3_NAME>
     <R3_SEQNUM>000015</R3_SEQNUM>
    </item>
    <item>
     <OBJECT>TABL</OBJECT>
     <OBJ_NAME>ZEBIZ_CHARGECUSTOMER</OBJ_NAME>
     <OBJECT1>FIEL</OBJECT1>
     <OBJ_NAME1>PHONE</OBJ_NAME1>
     <OBJECT2>FIEL</OBJECT2>
     <OBJ_NAME2>PHONE</OBJ_NAME2>
     <ID>&lt;element&gt; {http://eBizCharge.ServiceModel.SOAP}Phone &lt;type&gt; Customer http://eBizCharge.ServiceModel.SOAP http://eBizCharge.ServiceModel.SOAP</ID>
     <IFR_TYPE>element</IFR_TYPE>
     <IFR_NAME>Phone</IFR_NAME>
     <IFR_TAGTYP>E</IFR_TAGTYP>
     <IFR_MAXOCC>1</IFR_MAXOCC>
     <IFR_OPTNL>X</IFR_OPTNL>
     <IFR_QUALIF>X</IFR_QUALIF>
     <IFR_XSDTYP>string</IFR_XSDTYP>
     <IFR_SCALE>-2</IFR_SCALE>
     <R3_TYPE>FIEL</R3_TYPE>
     <R3_NAME>PHONE</R3_NAME>
     <R3_DATATYP>STRG</R3_DATATYP>
     <R3_SEQNUM>000007</R3_SEQNUM>
    </item>
    <item>
     <OBJECT>TABL</OBJECT>
     <OBJ_NAME>ZEBIZ_CHARGECUSTOMER</OBJ_NAME>
     <OBJECT1>FIEL</OBJECT1>
     <OBJ_NAME1>RECURRING_BILLING_DATA</OBJ_NAME1>
     <OBJECT2>FIEL</OBJECT2>
     <OBJ_NAME2>RECURRING_BILLING_DATA</OBJ_NAME2>
     <OBJECT_R>TABL</OBJECT_R>
     <OBJ_NAME_R>ZEBIZ_CHARGEARRAY_OF_RECURRIN1</OBJ_NAME_R>
     <ID>&lt;element&gt; {http://eBizCharge.ServiceModel.SOAP}RecurringBillingData &lt;type&gt; Customer http://eBizCharge.ServiceModel.SOAP http://eBizCharge.ServiceModel.SOAP</ID>
     <IFR_TYPE>element</IFR_TYPE>
     <IFR_NAME>RecurringBillingData</IFR_NAME>
     <IFR_TAGTYP>E</IFR_TAGTYP>
     <IFR_MAXOCC>1</IFR_MAXOCC>
     <IFR_OPTNL>X</IFR_OPTNL>
     <IFR_QUALIF>X</IFR_QUALIF>
     <IFR_SCALE>-2</IFR_SCALE>
     <R3_TYPE>FIEL</R3_TYPE>
     <R3_NAME>RECURRING_BILLING_DATA</R3_NAME>
     <R3_SEQNUM>000012</R3_SEQNUM>
    </item>
    <item>
     <OBJECT>TABL</OBJECT>
     <OBJ_NAME>ZEBIZ_CHARGECUSTOMER</OBJ_NAME>
     <OBJECT1>FIEL</OBJECT1>
     <OBJ_NAME1>SHIPPING_ADDRESS</OBJ_NAME1>
     <OBJECT2>FIEL</OBJECT2>
     <OBJ_NAME2>SHIPPING_ADDRESS</OBJ_NAME2>
     <OBJECT_R>TABL</OBJECT_R>
     <OBJ_NAME_R>ZEBIZ_CHARGEADDRESS</OBJ_NAME_R>
     <ID>&lt;element&gt; {http://eBizCharge.ServiceModel.SOAP}ShippingAddress &lt;type&gt; Customer http://eBizCharge.ServiceModel.SOAP http://eBizCharge.ServiceModel.SOAP</ID>
     <IFR_TYPE>element</IFR_TYPE>
     <IFR_NAME>ShippingAddress</IFR_NAME>
     <IFR_TAGTYP>E</IFR_TAGTYP>
     <IFR_MAXOCC>1</IFR_MAXOCC>
     <IFR_OPTNL>X</IFR_OPTNL>
     <IFR_QUALIF>X</IFR_QUALIF>
     <IFR_SCALE>-2</IFR_SCALE>
     <R3_TYPE>FIEL</R3_TYPE>
     <R3_NAME>SHIPPING_ADDRESS</R3_NAME>
     <R3_SEQNUM>000014</R3_SEQNUM>
    </item>
    <item>
     <OBJECT>TABL</OBJECT>
     <OBJ_NAME>ZEBIZ_CHARGECUSTOMER</OBJ_NAME>
     <OBJECT1>FIEL</OBJECT1>
     <OBJ_NAME1>SOFTWARE_ID</OBJ_NAME1>
     <OBJECT2>FIEL</OBJECT2>
     <OBJ_NAME2>SOFTWARE_ID</OBJ_NAME2>
     <ID>&lt;element&gt; {http://eBizCharge.ServiceModel.SOAP}SoftwareId &lt;type&gt; Customer http://eBizCharge.ServiceModel.SOAP http://eBizCharge.ServiceModel.SOAP</ID>
     <IFR_TYPE>element</IFR_TYPE>
     <IFR_NAME>SoftwareId</IFR_NAME>
     <IFR_TAGTYP>E</IFR_TAGTYP>
     <IFR_MAXOCC>1</IFR_MAXOCC>
     <IFR_OPTNL>X</IFR_OPTNL>
     <IFR_QUALIF>X</IFR_QUALIF>
     <IFR_XSDTYP>string</IFR_XSDTYP>
     <IFR_SCALE>-2</IFR_SCALE>
     <R3_TYPE>FIEL</R3_TYPE>
     <R3_NAME>SOFTWARE_ID</R3_NAME>
     <R3_DATATYP>STRG</R3_DATATYP>
     <R3_SEQNUM>000018</R3_SEQNUM>
    </item>
    <item>
     <OBJECT>TABL</OBJECT>
     <OBJ_NAME>ZEBIZ_CHARGECUSTOMER</OBJ_NAME>
     <OBJECT1>FIEL</OBJECT1>
     <OBJ_NAME1>WEB_SITE</OBJ_NAME1>
     <OBJECT2>FIEL</OBJECT2>
     <OBJ_NAME2>WEB_SITE</OBJ_NAME2>
     <ID>&lt;element&gt; {http://eBizCharge.ServiceModel.SOAP}WebSite &lt;type&gt; Customer http://eBizCharge.ServiceModel.SOAP http://eBizCharge.ServiceModel.SOAP</ID>
     <IFR_TYPE>element</IFR_TYPE>
     <IFR_NAME>WebSite</IFR_NAME>
     <IFR_TAGTYP>E</IFR_TAGTYP>
     <IFR_MAXOCC>1</IFR_MAXOCC>
     <IFR_OPTNL>X</IFR_OPTNL>
     <IFR_QUALIF>X</IFR_QUALIF>
     <IFR_XSDTYP>string</IFR_XSDTYP>
     <IFR_SCALE>-2</IFR_SCALE>
     <R3_TYPE>FIEL</R3_TYPE>
     <R3_NAME>WEB_SITE</R3_NAME>
     <R3_DATATYP>STRG</R3_DATATYP>
     <R3_SEQNUM>000011</R3_SEQNUM>
    </item>
    <item>
     <OBJECT>TABL</OBJECT>
     <OBJ_NAME>ZEBIZ_CHARGECUSTOMER</OBJ_NAME>
     <OBJECT1>TABL</OBJECT1>
     <OBJ_NAME1>ZEBIZ_CHARGECUSTOMER</OBJ_NAME1>
     <OBJECT2>TABL</OBJECT2>
     <OBJ_NAME2>ZEBIZ_CHARGECUSTOMER</OBJ_NAME2>
     <ID>&lt;type&gt; Customer http://eBizCharge.ServiceModel.SOAP http://eBizCharge.ServiceModel.SOAP</ID>
     <IFR_TYPE>type</IFR_TYPE>
     <IFR_NAME>Customer</IFR_NAME>
     <IFR_SCALE>-2</IFR_SCALE>
     <R3_TYPE>TABL</R3_TYPE>
     <R3_NAME>ZEBIZ_CHARGECUSTOMER</R3_NAME>
     <R3_TEXT>Proxy Structure (generated)</R3_TEXT>
     <CATEGORY>ifmtypedef</CATEGORY>
    </item>
   </PROXY_DATA>
  </asx:values>
 </asx:abap>
</abapGit>
