<?xml version="1.0" encoding="utf-8"?>
<abapGit version="v1.0.0" serializer="LCL_OBJECT_SPRX" serializer_version="v1.0.0">
 <asx:abap xmlns:asx="http://www.sap.com/abapxml" version="1.0">
  <asx:values>
   <PROXY_HEADER>
    <item>
     <OBJECT>TABL</OBJECT>
     <OBJ_NAME>ZEBIZ_CHARGESALES_ORDER</OBJ_NAME>
     <OBJECT_M>TABL</OBJECT_M>
     <OBJ_NAME_M>ZEBIZ_CHARGESALES_ORDER</OBJ_NAME_M>
     <HASH_ID>4DA793D5E0207983B3C3BAD94BE048A47C737C6F</HASH_ID>
     <ID>&lt;type&gt; SalesOrder http://eBizCharge.ServiceModel.SOAP http://eBizCharge.ServiceModel.SOAP</ID>
     <IFR_GLOBAL>X</IFR_GLOBAL>
     <IFR_TYPE>type</IFR_TYPE>
     <IFR_NAME>SalesOrder</IFR_NAME>
     <IFR_NSPCE>http://eBizCharge.ServiceModel.SOAP</IFR_NSPCE>
     <IFR_GNSPCE>http://eBizCharge.ServiceModel.SOAP</IFR_GNSPCE>
     <GEN_VERS>0005</GEN_VERS>
     <PREFIX>ZEBIZ_CHARGE</PREFIX>
     <CATEGORY>ifmtypedef</CATEGORY>
     <GEN_APPL>WEBSERVICES</GEN_APPL>
     <X-ML_NSPCE>http://eBizCharge.ServiceModel.SOAP</X-ML_NSPCE>
     <X-ML_NAME>SalesOrder</X-ML_NAME>
    </item>
   </PROXY_HEADER>
   <PROXY_DATA>
    <item>
     <OBJECT>TABL</OBJECT>
     <OBJ_NAME>ZEBIZ_CHARGESALES_ORDER</OBJ_NAME>
     <OBJECT1>FIEL</OBJECT1>
     <OBJ_NAME1>AMOUNT</OBJ_NAME1>
     <OBJECT2>FIEL</OBJECT2>
     <OBJ_NAME2>AMOUNT</OBJ_NAME2>
     <ID>&lt;element&gt; {http://eBizCharge.ServiceModel.SOAP}Amount &lt;type&gt; SalesOrder http://eBizCharge.ServiceModel.SOAP http://eBizCharge.ServiceModel.SOAP</ID>
     <IFR_TYPE>element</IFR_TYPE>
     <IFR_NAME>Amount</IFR_NAME>
     <IFR_TAGTYP>E</IFR_TAGTYP>
     <IFR_MINOCC>1</IFR_MINOCC>
     <IFR_MAXOCC>1</IFR_MAXOCC>
     <IFR_QUALIF>X</IFR_QUALIF>
     <IFR_XSDTYP>decimal</IFR_XSDTYP>
     <IFR_NILLABLE>X</IFR_NILLABLE>
     <IFR_SCALE>-2</IFR_SCALE>
     <R3_TYPE>FIEL</R3_TYPE>
     <R3_NAME>AMOUNT</R3_NAME>
     <R3_DATATYP>STRG</R3_DATATYP>
     <R3_SEQNUM>000008</R3_SEQNUM>
    </item>
    <item>
     <OBJECT>TABL</OBJECT>
     <OBJ_NAME>ZEBIZ_CHARGESALES_ORDER</OBJ_NAME>
     <OBJECT1>FIEL</OBJECT1>
     <OBJ_NAME1>AMOUNT_DUE</OBJ_NAME1>
     <OBJECT2>FIEL</OBJECT2>
     <OBJ_NAME2>AMOUNT_DUE</OBJ_NAME2>
     <ID>&lt;element&gt; {http://eBizCharge.ServiceModel.SOAP}AmountDue &lt;type&gt; SalesOrder http://eBizCharge.ServiceModel.SOAP http://eBizCharge.ServiceModel.SOAP</ID>
     <IFR_TYPE>element</IFR_TYPE>
     <IFR_NAME>AmountDue</IFR_NAME>
     <IFR_TAGTYP>E</IFR_TAGTYP>
     <IFR_MINOCC>1</IFR_MINOCC>
     <IFR_MAXOCC>1</IFR_MAXOCC>
     <IFR_QUALIF>X</IFR_QUALIF>
     <IFR_XSDTYP>decimal</IFR_XSDTYP>
     <IFR_NILLABLE>X</IFR_NILLABLE>
     <IFR_SCALE>-2</IFR_SCALE>
     <R3_TYPE>FIEL</R3_TYPE>
     <R3_NAME>AMOUNT_DUE</R3_NAME>
     <R3_DATATYP>STRG</R3_DATATYP>
     <R3_SEQNUM>000010</R3_SEQNUM>
    </item>
    <item>
     <OBJECT>TABL</OBJECT>
     <OBJ_NAME>ZEBIZ_CHARGESALES_ORDER</OBJ_NAME>
     <OBJECT1>FIEL</OBJECT1>
     <OBJ_NAME1>BILLING_ADDRESS</OBJ_NAME1>
     <OBJECT2>FIEL</OBJECT2>
     <OBJ_NAME2>BILLING_ADDRESS</OBJ_NAME2>
     <OBJECT_R>TABL</OBJECT_R>
     <OBJ_NAME_R>ZEBIZ_CHARGEADDRESS</OBJ_NAME_R>
     <ID>&lt;element&gt; {http://eBizCharge.ServiceModel.SOAP}BillingAddress &lt;type&gt; SalesOrder http://eBizCharge.ServiceModel.SOAP http://eBizCharge.ServiceModel.SOAP</ID>
     <IFR_TYPE>element</IFR_TYPE>
     <IFR_NAME>BillingAddress</IFR_NAME>
     <IFR_TAGTYP>E</IFR_TAGTYP>
     <IFR_MAXOCC>1</IFR_MAXOCC>
     <IFR_OPTNL>X</IFR_OPTNL>
     <IFR_QUALIF>X</IFR_QUALIF>
     <IFR_SCALE>-2</IFR_SCALE>
     <R3_TYPE>FIEL</R3_TYPE>
     <R3_NAME>BILLING_ADDRESS</R3_NAME>
     <R3_SEQNUM>000029</R3_SEQNUM>
    </item>
    <item>
     <OBJECT>TABL</OBJECT>
     <OBJ_NAME>ZEBIZ_CHARGESALES_ORDER</OBJ_NAME>
     <OBJECT1>FIEL</OBJECT1>
     <OBJ_NAME1>CURRENCY</OBJ_NAME1>
     <OBJECT2>FIEL</OBJECT2>
     <OBJ_NAME2>CURRENCY</OBJ_NAME2>
     <ID>&lt;element&gt; {http://eBizCharge.ServiceModel.SOAP}Currency &lt;type&gt; SalesOrder http://eBizCharge.ServiceModel.SOAP http://eBizCharge.ServiceModel.SOAP</ID>
     <IFR_TYPE>element</IFR_TYPE>
     <IFR_NAME>Currency</IFR_NAME>
     <IFR_TAGTYP>E</IFR_TAGTYP>
     <IFR_MAXOCC>1</IFR_MAXOCC>
     <IFR_OPTNL>X</IFR_OPTNL>
     <IFR_QUALIF>X</IFR_QUALIF>
     <IFR_XSDTYP>string</IFR_XSDTYP>
     <IFR_SCALE>-2</IFR_SCALE>
     <R3_TYPE>FIEL</R3_TYPE>
     <R3_NAME>CURRENCY</R3_NAME>
     <R3_DATATYP>STRG</R3_DATATYP>
     <R3_SEQNUM>000007</R3_SEQNUM>
    </item>
    <item>
     <OBJECT>TABL</OBJECT>
     <OBJ_NAME>ZEBIZ_CHARGESALES_ORDER</OBJ_NAME>
     <OBJECT1>FIEL</OBJECT1>
     <OBJ_NAME1>CUSTOMER_ID</OBJ_NAME1>
     <OBJECT2>FIEL</OBJECT2>
     <OBJ_NAME2>CUSTOMER_ID</OBJ_NAME2>
     <ID>&lt;element&gt; {http://eBizCharge.ServiceModel.SOAP}CustomerId &lt;type&gt; SalesOrder http://eBizCharge.ServiceModel.SOAP http://eBizCharge.ServiceModel.SOAP</ID>
     <IFR_TYPE>element</IFR_TYPE>
     <IFR_NAME>CustomerId</IFR_NAME>
     <IFR_TAGTYP>E</IFR_TAGTYP>
     <IFR_MAXOCC>1</IFR_MAXOCC>
     <IFR_OPTNL>X</IFR_OPTNL>
     <IFR_QUALIF>X</IFR_QUALIF>
     <IFR_XSDTYP>string</IFR_XSDTYP>
     <IFR_SCALE>-2</IFR_SCALE>
     <R3_TYPE>FIEL</R3_TYPE>
     <R3_NAME>CUSTOMER_ID</R3_NAME>
     <R3_DATATYP>STRG</R3_DATATYP>
     <R3_SEQNUM>000002</R3_SEQNUM>
    </item>
    <item>
     <OBJECT>TABL</OBJECT>
     <OBJ_NAME>ZEBIZ_CHARGESALES_ORDER</OBJ_NAME>
     <OBJECT1>FIEL</OBJECT1>
     <OBJ_NAME1>CUSTOMER_MESSAGE</OBJ_NAME1>
     <OBJECT2>FIEL</OBJECT2>
     <OBJ_NAME2>CUSTOMER_MESSAGE</OBJ_NAME2>
     <ID>&lt;element&gt; {http://eBizCharge.ServiceModel.SOAP}CustomerMessage &lt;type&gt; SalesOrder http://eBizCharge.ServiceModel.SOAP http://eBizCharge.ServiceModel.SOAP</ID>
     <IFR_TYPE>element</IFR_TYPE>
     <IFR_NAME>CustomerMessage</IFR_NAME>
     <IFR_TAGTYP>E</IFR_TAGTYP>
     <IFR_MAXOCC>1</IFR_MAXOCC>
     <IFR_OPTNL>X</IFR_OPTNL>
     <IFR_QUALIF>X</IFR_QUALIF>
     <IFR_XSDTYP>string</IFR_XSDTYP>
     <IFR_SCALE>-2</IFR_SCALE>
     <R3_TYPE>FIEL</R3_TYPE>
     <R3_NAME>CUSTOMER_MESSAGE</R3_NAME>
     <R3_DATATYP>STRG</R3_DATATYP>
     <R3_SEQNUM>000031</R3_SEQNUM>
    </item>
    <item>
     <OBJECT>TABL</OBJECT>
     <OBJ_NAME>ZEBIZ_CHARGESALES_ORDER</OBJ_NAME>
     <OBJECT1>FIEL</OBJECT1>
     <OBJ_NAME1>DATE</OBJ_NAME1>
     <OBJECT2>FIEL</OBJECT2>
     <OBJ_NAME2>DATE</OBJ_NAME2>
     <ID>&lt;element&gt; {http://eBizCharge.ServiceModel.SOAP}Date &lt;type&gt; SalesOrder http://eBizCharge.ServiceModel.SOAP http://eBizCharge.ServiceModel.SOAP</ID>
     <IFR_TYPE>element</IFR_TYPE>
     <IFR_NAME>Date</IFR_NAME>
     <IFR_TAGTYP>E</IFR_TAGTYP>
     <IFR_MAXOCC>1</IFR_MAXOCC>
     <IFR_OPTNL>X</IFR_OPTNL>
     <IFR_QUALIF>X</IFR_QUALIF>
     <IFR_XSDTYP>string</IFR_XSDTYP>
     <IFR_SCALE>-2</IFR_SCALE>
     <R3_TYPE>FIEL</R3_TYPE>
     <R3_NAME>DATE</R3_NAME>
     <R3_DATATYP>STRG</R3_DATATYP>
     <R3_SEQNUM>000006</R3_SEQNUM>
    </item>
    <item>
     <OBJECT>TABL</OBJECT>
     <OBJ_NAME>ZEBIZ_CHARGESALES_ORDER</OBJ_NAME>
     <OBJECT1>FIEL</OBJECT1>
     <OBJ_NAME1>DATE_DELETED</OBJ_NAME1>
     <OBJECT2>FIEL</OBJECT2>
     <OBJ_NAME2>DATE_DELETED</OBJ_NAME2>
     <ID>&lt;element&gt; {http://eBizCharge.ServiceModel.SOAP}DateDeleted &lt;type&gt; SalesOrder http://eBizCharge.ServiceModel.SOAP http://eBizCharge.ServiceModel.SOAP</ID>
     <IFR_TYPE>element</IFR_TYPE>
     <IFR_NAME>DateDeleted</IFR_NAME>
     <IFR_TAGTYP>E</IFR_TAGTYP>
     <IFR_MAXOCC>1</IFR_MAXOCC>
     <IFR_OPTNL>X</IFR_OPTNL>
     <IFR_QUALIF>X</IFR_QUALIF>
     <IFR_XSDTYP>string</IFR_XSDTYP>
     <IFR_SCALE>-2</IFR_SCALE>
     <R3_TYPE>FIEL</R3_TYPE>
     <R3_NAME>DATE_DELETED</R3_NAME>
     <R3_DATATYP>STRG</R3_DATATYP>
     <R3_SEQNUM>000020</R3_SEQNUM>
    </item>
    <item>
     <OBJECT>TABL</OBJECT>
     <OBJ_NAME>ZEBIZ_CHARGESALES_ORDER</OBJ_NAME>
     <OBJECT1>FIEL</OBJECT1>
     <OBJ_NAME1>DATE_UPDATED</OBJ_NAME1>
     <OBJECT2>FIEL</OBJECT2>
     <OBJ_NAME2>DATE_UPDATED</OBJ_NAME2>
     <ID>&lt;element&gt; {http://eBizCharge.ServiceModel.SOAP}DateUpdated &lt;type&gt; SalesOrder http://eBizCharge.ServiceModel.SOAP http://eBizCharge.ServiceModel.SOAP</ID>
     <IFR_TYPE>element</IFR_TYPE>
     <IFR_NAME>DateUpdated</IFR_NAME>
     <IFR_TAGTYP>E</IFR_TAGTYP>
     <IFR_MAXOCC>1</IFR_MAXOCC>
     <IFR_OPTNL>X</IFR_OPTNL>
     <IFR_QUALIF>X</IFR_QUALIF>
     <IFR_XSDTYP>string</IFR_XSDTYP>
     <IFR_SCALE>-2</IFR_SCALE>
     <R3_TYPE>FIEL</R3_TYPE>
     <R3_NAME>DATE_UPDATED</R3_NAME>
     <R3_DATATYP>STRG</R3_DATATYP>
     <R3_SEQNUM>000017</R3_SEQNUM>
    </item>
    <item>
     <OBJECT>TABL</OBJECT>
     <OBJ_NAME>ZEBIZ_CHARGESALES_ORDER</OBJ_NAME>
     <OBJECT1>FIEL</OBJECT1>
     <OBJ_NAME1>DATE_UPLOADED</OBJ_NAME1>
     <OBJECT2>FIEL</OBJECT2>
     <OBJ_NAME2>DATE_UPLOADED</OBJ_NAME2>
     <ID>&lt;element&gt; {http://eBizCharge.ServiceModel.SOAP}DateUploaded &lt;type&gt; SalesOrder http://eBizCharge.ServiceModel.SOAP http://eBizCharge.ServiceModel.SOAP</ID>
     <IFR_TYPE>element</IFR_TYPE>
     <IFR_NAME>DateUploaded</IFR_NAME>
     <IFR_TAGTYP>E</IFR_TAGTYP>
     <IFR_MAXOCC>1</IFR_MAXOCC>
     <IFR_OPTNL>X</IFR_OPTNL>
     <IFR_QUALIF>X</IFR_QUALIF>
     <IFR_XSDTYP>string</IFR_XSDTYP>
     <IFR_SCALE>-2</IFR_SCALE>
     <R3_TYPE>FIEL</R3_TYPE>
     <R3_NAME>DATE_UPLOADED</R3_NAME>
     <R3_DATATYP>STRG</R3_DATATYP>
     <R3_SEQNUM>000016</R3_SEQNUM>
    </item>
    <item>
     <OBJECT>TABL</OBJECT>
     <OBJ_NAME>ZEBIZ_CHARGESALES_ORDER</OBJ_NAME>
     <OBJECT1>FIEL</OBJECT1>
     <OBJ_NAME1>DELETED_BY</OBJ_NAME1>
     <OBJECT2>FIEL</OBJECT2>
     <OBJ_NAME2>DELETED_BY</OBJ_NAME2>
     <ID>&lt;element&gt; {http://eBizCharge.ServiceModel.SOAP}DeletedBy &lt;type&gt; SalesOrder http://eBizCharge.ServiceModel.SOAP http://eBizCharge.ServiceModel.SOAP</ID>
     <IFR_TYPE>element</IFR_TYPE>
     <IFR_NAME>DeletedBy</IFR_NAME>
     <IFR_TAGTYP>E</IFR_TAGTYP>
     <IFR_MAXOCC>1</IFR_MAXOCC>
     <IFR_OPTNL>X</IFR_OPTNL>
     <IFR_QUALIF>X</IFR_QUALIF>
     <IFR_XSDTYP>string</IFR_XSDTYP>
     <IFR_SCALE>-2</IFR_SCALE>
     <R3_TYPE>FIEL</R3_TYPE>
     <R3_NAME>DELETED_BY</R3_NAME>
     <R3_DATATYP>STRG</R3_DATATYP>
     <R3_SEQNUM>000019</R3_SEQNUM>
    </item>
    <item>
     <OBJECT>TABL</OBJECT>
     <OBJ_NAME>ZEBIZ_CHARGESALES_ORDER</OBJ_NAME>
     <OBJECT1>FIEL</OBJECT1>
     <OBJ_NAME1>DESCRIPTION</OBJ_NAME1>
     <OBJECT2>FIEL</OBJECT2>
     <OBJ_NAME2>DESCRIPTION</OBJ_NAME2>
     <ID>&lt;element&gt; {http://eBizCharge.ServiceModel.SOAP}Description &lt;type&gt; SalesOrder http://eBizCharge.ServiceModel.SOAP http://eBizCharge.ServiceModel.SOAP</ID>
     <IFR_TYPE>element</IFR_TYPE>
     <IFR_NAME>Description</IFR_NAME>
     <IFR_TAGTYP>E</IFR_TAGTYP>
     <IFR_MAXOCC>1</IFR_MAXOCC>
     <IFR_OPTNL>X</IFR_OPTNL>
     <IFR_QUALIF>X</IFR_QUALIF>
     <IFR_XSDTYP>string</IFR_XSDTYP>
     <IFR_SCALE>-2</IFR_SCALE>
     <R3_TYPE>FIEL</R3_TYPE>
     <R3_NAME>DESCRIPTION</R3_NAME>
     <R3_DATATYP>STRG</R3_DATATYP>
     <R3_SEQNUM>000028</R3_SEQNUM>
    </item>
    <item>
     <OBJECT>TABL</OBJECT>
     <OBJ_NAME>ZEBIZ_CHARGESALES_ORDER</OBJ_NAME>
     <OBJECT1>FIEL</OBJECT1>
     <OBJ_NAME1>DIVISION_ID</OBJ_NAME1>
     <OBJECT2>FIEL</OBJECT2>
     <OBJ_NAME2>DIVISION_ID</OBJ_NAME2>
     <ID>&lt;element&gt; {http://eBizCharge.ServiceModel.SOAP}DivisionId &lt;type&gt; SalesOrder http://eBizCharge.ServiceModel.SOAP http://eBizCharge.ServiceModel.SOAP</ID>
     <IFR_TYPE>element</IFR_TYPE>
     <IFR_NAME>DivisionId</IFR_NAME>
     <IFR_TAGTYP>E</IFR_TAGTYP>
     <IFR_MAXOCC>1</IFR_MAXOCC>
     <IFR_OPTNL>X</IFR_OPTNL>
     <IFR_QUALIF>X</IFR_QUALIF>
     <IFR_XSDTYP>string</IFR_XSDTYP>
     <IFR_SCALE>-2</IFR_SCALE>
     <R3_TYPE>FIEL</R3_TYPE>
     <R3_NAME>DIVISION_ID</R3_NAME>
     <R3_DATATYP>STRG</R3_DATATYP>
     <R3_SEQNUM>000012</R3_SEQNUM>
    </item>
    <item>
     <OBJECT>TABL</OBJECT>
     <OBJ_NAME>ZEBIZ_CHARGESALES_ORDER</OBJ_NAME>
     <OBJECT1>FIEL</OBJECT1>
     <OBJ_NAME1>DUE_DATE</OBJ_NAME1>
     <OBJECT2>FIEL</OBJECT2>
     <OBJ_NAME2>DUE_DATE</OBJ_NAME2>
     <ID>&lt;element&gt; {http://eBizCharge.ServiceModel.SOAP}DueDate &lt;type&gt; SalesOrder http://eBizCharge.ServiceModel.SOAP http://eBizCharge.ServiceModel.SOAP</ID>
     <IFR_TYPE>element</IFR_TYPE>
     <IFR_NAME>DueDate</IFR_NAME>
     <IFR_TAGTYP>E</IFR_TAGTYP>
     <IFR_MAXOCC>1</IFR_MAXOCC>
     <IFR_OPTNL>X</IFR_OPTNL>
     <IFR_QUALIF>X</IFR_QUALIF>
     <IFR_XSDTYP>string</IFR_XSDTYP>
     <IFR_SCALE>-2</IFR_SCALE>
     <R3_TYPE>FIEL</R3_TYPE>
     <R3_NAME>DUE_DATE</R3_NAME>
     <R3_DATATYP>STRG</R3_DATATYP>
     <R3_SEQNUM>000009</R3_SEQNUM>
    </item>
    <item>
     <OBJECT>TABL</OBJECT>
     <OBJ_NAME>ZEBIZ_CHARGESALES_ORDER</OBJ_NAME>
     <OBJECT1>FIEL</OBJECT1>
     <OBJ_NAME1>EMAIL_TEMPLATE_ID</OBJ_NAME1>
     <OBJECT2>FIEL</OBJECT2>
     <OBJ_NAME2>EMAIL_TEMPLATE_ID</OBJ_NAME2>
     <ID>&lt;element&gt; {http://eBizCharge.ServiceModel.SOAP}EmailTemplateID &lt;type&gt; SalesOrder http://eBizCharge.ServiceModel.SOAP http://eBizCharge.ServiceModel.SOAP</ID>
     <IFR_TYPE>element</IFR_TYPE>
     <IFR_NAME>EmailTemplateID</IFR_NAME>
     <IFR_TAGTYP>E</IFR_TAGTYP>
     <IFR_MAXOCC>1</IFR_MAXOCC>
     <IFR_OPTNL>X</IFR_OPTNL>
     <IFR_QUALIF>X</IFR_QUALIF>
     <IFR_XSDTYP>string</IFR_XSDTYP>
     <IFR_SCALE>-2</IFR_SCALE>
     <R3_TYPE>FIEL</R3_TYPE>
     <R3_NAME>EMAIL_TEMPLATE_ID</R3_NAME>
     <R3_DATATYP>STRG</R3_DATATYP>
     <R3_SEQNUM>000024</R3_SEQNUM>
    </item>
    <item>
     <OBJECT>TABL</OBJECT>
     <OBJ_NAME>ZEBIZ_CHARGESALES_ORDER</OBJ_NAME>
     <OBJECT1>FIEL</OBJECT1>
     <OBJ_NAME1>IS_DELETED</OBJ_NAME1>
     <OBJECT2>FIEL</OBJECT2>
     <OBJ_NAME2>IS_DELETED</OBJ_NAME2>
     <ID>&lt;element&gt; {http://eBizCharge.ServiceModel.SOAP}isDeleted &lt;type&gt; SalesOrder http://eBizCharge.ServiceModel.SOAP http://eBizCharge.ServiceModel.SOAP</ID>
     <IFR_TYPE>element</IFR_TYPE>
     <IFR_NAME>isDeleted</IFR_NAME>
     <IFR_TAGTYP>E</IFR_TAGTYP>
     <IFR_MAXOCC>1</IFR_MAXOCC>
     <IFR_OPTNL>X</IFR_OPTNL>
     <IFR_QUALIF>X</IFR_QUALIF>
     <IFR_XSDTYP>string</IFR_XSDTYP>
     <IFR_SCALE>-2</IFR_SCALE>
     <R3_TYPE>FIEL</R3_TYPE>
     <R3_NAME>IS_DELETED</R3_NAME>
     <R3_DATATYP>STRG</R3_DATATYP>
     <R3_SEQNUM>000018</R3_SEQNUM>
    </item>
    <item>
     <OBJECT>TABL</OBJECT>
     <OBJ_NAME>ZEBIZ_CHARGESALES_ORDER</OBJ_NAME>
     <OBJECT1>FIEL</OBJECT1>
     <OBJ_NAME1>IS_TO_BE_EMAILED</OBJ_NAME1>
     <OBJECT2>FIEL</OBJECT2>
     <OBJ_NAME2>IS_TO_BE_EMAILED</OBJ_NAME2>
     <ID>&lt;element&gt; {http://eBizCharge.ServiceModel.SOAP}IsToBeEmailed &lt;type&gt; SalesOrder http://eBizCharge.ServiceModel.SOAP http://eBizCharge.ServiceModel.SOAP</ID>
     <IFR_TYPE>element</IFR_TYPE>
     <IFR_NAME>IsToBeEmailed</IFR_NAME>
     <IFR_TAGTYP>E</IFR_TAGTYP>
     <IFR_MINOCC>1</IFR_MINOCC>
     <IFR_MAXOCC>1</IFR_MAXOCC>
     <IFR_QUALIF>X</IFR_QUALIF>
     <IFR_XSDTYP>boolean</IFR_XSDTYP>
     <IFR_NILLABLE>X</IFR_NILLABLE>
     <IFR_SCALE>-2</IFR_SCALE>
     <R3_TYPE>FIEL</R3_TYPE>
     <R3_NAME>IS_TO_BE_EMAILED</R3_NAME>
     <R3_DTREF>XSDBOOLEAN</R3_DTREF>
     <R3_SEQNUM>000037</R3_SEQNUM>
    </item>
    <item>
     <OBJECT>TABL</OBJECT>
     <OBJ_NAME>ZEBIZ_CHARGESALES_ORDER</OBJ_NAME>
     <OBJECT1>FIEL</OBJECT1>
     <OBJ_NAME1>IS_TO_BE_PRINTED</OBJ_NAME1>
     <OBJECT2>FIEL</OBJECT2>
     <OBJ_NAME2>IS_TO_BE_PRINTED</OBJ_NAME2>
     <ID>&lt;element&gt; {http://eBizCharge.ServiceModel.SOAP}IsToBePrinted &lt;type&gt; SalesOrder http://eBizCharge.ServiceModel.SOAP http://eBizCharge.ServiceModel.SOAP</ID>
     <IFR_TYPE>element</IFR_TYPE>
     <IFR_NAME>IsToBePrinted</IFR_NAME>
     <IFR_TAGTYP>E</IFR_TAGTYP>
     <IFR_MINOCC>1</IFR_MINOCC>
     <IFR_MAXOCC>1</IFR_MAXOCC>
     <IFR_QUALIF>X</IFR_QUALIF>
     <IFR_XSDTYP>boolean</IFR_XSDTYP>
     <IFR_NILLABLE>X</IFR_NILLABLE>
     <IFR_SCALE>-2</IFR_SCALE>
     <R3_TYPE>FIEL</R3_TYPE>
     <R3_NAME>IS_TO_BE_PRINTED</R3_NAME>
     <R3_DTREF>XSDBOOLEAN</R3_DTREF>
     <R3_SEQNUM>000038</R3_SEQNUM>
    </item>
    <item>
     <OBJECT>TABL</OBJECT>
     <OBJ_NAME>ZEBIZ_CHARGESALES_ORDER</OBJ_NAME>
     <OBJECT1>FIEL</OBJECT1>
     <OBJ_NAME1>ITEMS</OBJ_NAME1>
     <OBJECT2>FIEL</OBJECT2>
     <OBJ_NAME2>ITEMS</OBJ_NAME2>
     <OBJECT_R>TABL</OBJECT_R>
     <OBJ_NAME_R>ZEBIZ_CHARGEARRAY_OF_ITEM</OBJ_NAME_R>
     <ID>&lt;element&gt; {http://eBizCharge.ServiceModel.SOAP}Items &lt;type&gt; SalesOrder http://eBizCharge.ServiceModel.SOAP http://eBizCharge.ServiceModel.SOAP</ID>
     <IFR_TYPE>element</IFR_TYPE>
     <IFR_NAME>Items</IFR_NAME>
     <IFR_TAGTYP>E</IFR_TAGTYP>
     <IFR_MAXOCC>1</IFR_MAXOCC>
     <IFR_OPTNL>X</IFR_OPTNL>
     <IFR_QUALIF>X</IFR_QUALIF>
     <IFR_SCALE>-2</IFR_SCALE>
     <R3_TYPE>FIEL</R3_TYPE>
     <R3_NAME>ITEMS</R3_NAME>
     <R3_SEQNUM>000021</R3_SEQNUM>
    </item>
    <item>
     <OBJECT>TABL</OBJECT>
     <OBJ_NAME>ZEBIZ_CHARGESALES_ORDER</OBJ_NAME>
     <OBJECT1>FIEL</OBJECT1>
     <OBJ_NAME1>LOCATION_ID</OBJ_NAME1>
     <OBJECT2>FIEL</OBJECT2>
     <OBJ_NAME2>LOCATION_ID</OBJ_NAME2>
     <ID>&lt;element&gt; {http://eBizCharge.ServiceModel.SOAP}LocationId &lt;type&gt; SalesOrder http://eBizCharge.ServiceModel.SOAP http://eBizCharge.ServiceModel.SOAP</ID>
     <IFR_TYPE>element</IFR_TYPE>
     <IFR_NAME>LocationId</IFR_NAME>
     <IFR_TAGTYP>E</IFR_TAGTYP>
     <IFR_MAXOCC>1</IFR_MAXOCC>
     <IFR_OPTNL>X</IFR_OPTNL>
     <IFR_QUALIF>X</IFR_QUALIF>
     <IFR_XSDTYP>string</IFR_XSDTYP>
     <IFR_SCALE>-2</IFR_SCALE>
     <R3_TYPE>FIEL</R3_TYPE>
     <R3_NAME>LOCATION_ID</R3_NAME>
     <R3_DATATYP>STRG</R3_DATATYP>
     <R3_SEQNUM>000041</R3_SEQNUM>
    </item>
    <item>
     <OBJECT>TABL</OBJECT>
     <OBJ_NAME>ZEBIZ_CHARGESALES_ORDER</OBJ_NAME>
     <OBJECT1>FIEL</OBJECT1>
     <OBJ_NAME1>MEMO</OBJ_NAME1>
     <OBJECT2>FIEL</OBJECT2>
     <OBJ_NAME2>MEMO</OBJ_NAME2>
     <ID>&lt;element&gt; {http://eBizCharge.ServiceModel.SOAP}Memo &lt;type&gt; SalesOrder http://eBizCharge.ServiceModel.SOAP http://eBizCharge.ServiceModel.SOAP</ID>
     <IFR_TYPE>element</IFR_TYPE>
     <IFR_NAME>Memo</IFR_NAME>
     <IFR_TAGTYP>E</IFR_TAGTYP>
     <IFR_MAXOCC>1</IFR_MAXOCC>
     <IFR_OPTNL>X</IFR_OPTNL>
     <IFR_QUALIF>X</IFR_QUALIF>
     <IFR_XSDTYP>string</IFR_XSDTYP>
     <IFR_SCALE>-2</IFR_SCALE>
     <R3_TYPE>FIEL</R3_TYPE>
     <R3_NAME>MEMO</R3_NAME>
     <R3_DATATYP>STRG</R3_DATATYP>
     <R3_SEQNUM>000032</R3_SEQNUM>
    </item>
    <item>
     <OBJECT>TABL</OBJECT>
     <OBJ_NAME>ZEBIZ_CHARGESALES_ORDER</OBJ_NAME>
     <OBJECT1>FIEL</OBJECT1>
     <OBJ_NAME1>MERCHANT_ID</OBJ_NAME1>
     <OBJECT2>FIEL</OBJECT2>
     <OBJ_NAME2>MERCHANT_ID</OBJ_NAME2>
     <ID>&lt;element&gt; {http://eBizCharge.ServiceModel.SOAP}MerchantId &lt;type&gt; SalesOrder http://eBizCharge.ServiceModel.SOAP http://eBizCharge.ServiceModel.SOAP</ID>
     <IFR_TYPE>element</IFR_TYPE>
     <IFR_NAME>MerchantId</IFR_NAME>
     <IFR_TAGTYP>E</IFR_TAGTYP>
     <IFR_MAXOCC>1</IFR_MAXOCC>
     <IFR_OPTNL>X</IFR_OPTNL>
     <IFR_QUALIF>X</IFR_QUALIF>
     <IFR_XSDTYP>string</IFR_XSDTYP>
     <IFR_SCALE>-2</IFR_SCALE>
     <R3_TYPE>FIEL</R3_TYPE>
     <R3_NAME>MERCHANT_ID</R3_NAME>
     <R3_DATATYP>STRG</R3_DATATYP>
     <R3_SEQNUM>000001</R3_SEQNUM>
    </item>
    <item>
     <OBJECT>TABL</OBJECT>
     <OBJ_NAME>ZEBIZ_CHARGESALES_ORDER</OBJ_NAME>
     <OBJECT1>FIEL</OBJECT1>
     <OBJ_NAME1>NOTIFY_CUSTOMER</OBJ_NAME1>
     <OBJECT2>FIEL</OBJECT2>
     <OBJ_NAME2>NOTIFY_CUSTOMER</OBJ_NAME2>
     <ID>&lt;element&gt; {http://eBizCharge.ServiceModel.SOAP}NotifyCustomer &lt;type&gt; SalesOrder http://eBizCharge.ServiceModel.SOAP http://eBizCharge.ServiceModel.SOAP</ID>
     <IFR_TYPE>element</IFR_TYPE>
     <IFR_NAME>NotifyCustomer</IFR_NAME>
     <IFR_TAGTYP>E</IFR_TAGTYP>
     <IFR_MINOCC>1</IFR_MINOCC>
     <IFR_MAXOCC>1</IFR_MAXOCC>
     <IFR_QUALIF>X</IFR_QUALIF>
     <IFR_XSDTYP>boolean</IFR_XSDTYP>
     <IFR_NILLABLE>X</IFR_NILLABLE>
     <IFR_SCALE>-2</IFR_SCALE>
     <R3_TYPE>FIEL</R3_TYPE>
     <R3_NAME>NOTIFY_CUSTOMER</R3_NAME>
     <R3_DTREF>XSDBOOLEAN</R3_DTREF>
     <R3_SEQNUM>000023</R3_SEQNUM>
    </item>
    <item>
     <OBJECT>TABL</OBJECT>
     <OBJ_NAME>ZEBIZ_CHARGESALES_ORDER</OBJ_NAME>
     <OBJECT1>FIEL</OBJECT1>
     <OBJ_NAME1>PO_NUM</OBJ_NAME1>
     <OBJECT2>FIEL</OBJECT2>
     <OBJ_NAME2>PO_NUM</OBJ_NAME2>
     <ID>&lt;element&gt; {http://eBizCharge.ServiceModel.SOAP}PoNum &lt;type&gt; SalesOrder http://eBizCharge.ServiceModel.SOAP http://eBizCharge.ServiceModel.SOAP</ID>
     <IFR_TYPE>element</IFR_TYPE>
     <IFR_NAME>PoNum</IFR_NAME>
     <IFR_TAGTYP>E</IFR_TAGTYP>
     <IFR_MAXOCC>1</IFR_MAXOCC>
     <IFR_OPTNL>X</IFR_OPTNL>
     <IFR_QUALIF>X</IFR_QUALIF>
     <IFR_XSDTYP>string</IFR_XSDTYP>
     <IFR_SCALE>-2</IFR_SCALE>
     <R3_TYPE>FIEL</R3_TYPE>
     <R3_NAME>PO_NUM</R3_NAME>
     <R3_DATATYP>STRG</R3_DATATYP>
     <R3_SEQNUM>000011</R3_SEQNUM>
    </item>
    <item>
     <OBJECT>TABL</OBJECT>
     <OBJ_NAME>ZEBIZ_CHARGESALES_ORDER</OBJ_NAME>
     <OBJECT1>FIEL</OBJECT1>
     <OBJ_NAME1>SALES_ORDER_CUSTOM_FIELDS</OBJ_NAME1>
     <OBJECT2>FIEL</OBJECT2>
     <OBJ_NAME2>SALES_ORDER_CUSTOM_FIELDS</OBJ_NAME2>
     <OBJECT_R>TABL</OBJECT_R>
     <OBJ_NAME_R>ZEBIZ_CHARGEARRAY_OF_EBIZ_CUST</OBJ_NAME_R>
     <ID>&lt;element&gt; {http://eBizCharge.ServiceModel.SOAP}SalesOrderCustomFields &lt;type&gt; SalesOrder http://eBizCharge.ServiceModel.SOAP http://eBizCharge.ServiceModel.SOAP</ID>
     <IFR_TYPE>element</IFR_TYPE>
     <IFR_NAME>SalesOrderCustomFields</IFR_NAME>
     <IFR_TAGTYP>E</IFR_TAGTYP>
     <IFR_MAXOCC>1</IFR_MAXOCC>
     <IFR_OPTNL>X</IFR_OPTNL>
     <IFR_QUALIF>X</IFR_QUALIF>
     <IFR_SCALE>-2</IFR_SCALE>
     <R3_TYPE>FIEL</R3_TYPE>
     <R3_NAME>SALES_ORDER_CUSTOM_FIELDS</R3_NAME>
     <R3_SEQNUM>000040</R3_SEQNUM>
    </item>
    <item>
     <OBJECT>TABL</OBJECT>
     <OBJ_NAME>ZEBIZ_CHARGESALES_ORDER</OBJ_NAME>
     <OBJECT1>FIEL</OBJECT1>
     <OBJ_NAME1>SALES_ORDER_INTERNAL_ID</OBJ_NAME1>
     <OBJECT2>FIEL</OBJECT2>
     <OBJ_NAME2>SALES_ORDER_INTERNAL_ID</OBJ_NAME2>
     <ID>&lt;element&gt; {http://eBizCharge.ServiceModel.SOAP}SalesOrderInternalId &lt;type&gt; SalesOrder http://eBizCharge.ServiceModel.SOAP http://eBizCharge.ServiceModel.SOAP</ID>
     <IFR_TYPE>element</IFR_TYPE>
     <IFR_NAME>SalesOrderInternalId</IFR_NAME>
     <IFR_TAGTYP>E</IFR_TAGTYP>
     <IFR_MAXOCC>1</IFR_MAXOCC>
     <IFR_OPTNL>X</IFR_OPTNL>
     <IFR_QUALIF>X</IFR_QUALIF>
     <IFR_XSDTYP>string</IFR_XSDTYP>
     <IFR_SCALE>-2</IFR_SCALE>
     <R3_TYPE>FIEL</R3_TYPE>
     <R3_NAME>SALES_ORDER_INTERNAL_ID</R3_NAME>
     <R3_DATATYP>STRG</R3_DATATYP>
     <R3_SEQNUM>000005</R3_SEQNUM>
    </item>
    <item>
     <OBJECT>TABL</OBJECT>
     <OBJ_NAME>ZEBIZ_CHARGESALES_ORDER</OBJ_NAME>
     <OBJECT1>FIEL</OBJECT1>
     <OBJ_NAME1>SALES_ORDER_LAST_SYNC_DATE_TIM</OBJ_NAME1>
     <OBJECT2>FIEL</OBJECT2>
     <OBJ_NAME2>SALES_ORDER_LAST_SYNC_DATE_TIM</OBJ_NAME2>
     <ID>&lt;element&gt; {http://eBizCharge.ServiceModel.SOAP}SalesOrderLastSyncDateTime &lt;type&gt; SalesOrder http://eBizCharge.ServiceModel.SOAP http://eBizCharge.ServiceModel.SOAP</ID>
     <IFR_TYPE>element</IFR_TYPE>
     <IFR_NAME>SalesOrderLastSyncDateTime</IFR_NAME>
     <IFR_TAGTYP>E</IFR_TAGTYP>
     <IFR_MAXOCC>1</IFR_MAXOCC>
     <IFR_OPTNL>X</IFR_OPTNL>
     <IFR_QUALIF>X</IFR_QUALIF>
     <IFR_XSDTYP>string</IFR_XSDTYP>
     <IFR_SCALE>-2</IFR_SCALE>
     <R3_TYPE>FIEL</R3_TYPE>
     <R3_NAME>SALES_ORDER_LAST_SYNC_DATE_TIM</R3_NAME>
     <R3_DATATYP>STRG</R3_DATATYP>
     <R3_SEQNUM>000039</R3_SEQNUM>
    </item>
    <item>
     <OBJECT>TABL</OBJECT>
     <OBJ_NAME>ZEBIZ_CHARGESALES_ORDER</OBJ_NAME>
     <OBJECT1>FIEL</OBJECT1>
     <OBJ_NAME1>SALES_ORDER_NUMBER</OBJ_NAME1>
     <OBJECT2>FIEL</OBJECT2>
     <OBJ_NAME2>SALES_ORDER_NUMBER</OBJ_NAME2>
     <ID>&lt;element&gt; {http://eBizCharge.ServiceModel.SOAP}SalesOrderNumber &lt;type&gt; SalesOrder http://eBizCharge.ServiceModel.SOAP http://eBizCharge.ServiceModel.SOAP</ID>
     <IFR_TYPE>element</IFR_TYPE>
     <IFR_NAME>SalesOrderNumber</IFR_NAME>
     <IFR_TAGTYP>E</IFR_TAGTYP>
     <IFR_MAXOCC>1</IFR_MAXOCC>
     <IFR_OPTNL>X</IFR_OPTNL>
     <IFR_QUALIF>X</IFR_QUALIF>
     <IFR_XSDTYP>string</IFR_XSDTYP>
     <IFR_SCALE>-2</IFR_SCALE>
     <R3_TYPE>FIEL</R3_TYPE>
     <R3_NAME>SALES_ORDER_NUMBER</R3_NAME>
     <R3_DATATYP>STRG</R3_DATATYP>
     <R3_SEQNUM>000004</R3_SEQNUM>
    </item>
    <item>
     <OBJECT>TABL</OBJECT>
     <OBJ_NAME>ZEBIZ_CHARGESALES_ORDER</OBJ_NAME>
     <OBJECT1>FIEL</OBJECT1>
     <OBJ_NAME1>SALES_REP_ID</OBJ_NAME1>
     <OBJECT2>FIEL</OBJECT2>
     <OBJ_NAME2>SALES_REP_ID</OBJ_NAME2>
     <ID>&lt;element&gt; {http://eBizCharge.ServiceModel.SOAP}SalesRepId &lt;type&gt; SalesOrder http://eBizCharge.ServiceModel.SOAP http://eBizCharge.ServiceModel.SOAP</ID>
     <IFR_TYPE>element</IFR_TYPE>
     <IFR_NAME>SalesRepId</IFR_NAME>
     <IFR_TAGTYP>E</IFR_TAGTYP>
     <IFR_MAXOCC>1</IFR_MAXOCC>
     <IFR_OPTNL>X</IFR_OPTNL>
     <IFR_QUALIF>X</IFR_QUALIF>
     <IFR_XSDTYP>string</IFR_XSDTYP>
     <IFR_SCALE>-2</IFR_SCALE>
     <R3_TYPE>FIEL</R3_TYPE>
     <R3_NAME>SALES_REP_ID</R3_NAME>
     <R3_DATATYP>STRG</R3_DATATYP>
     <R3_SEQNUM>000035</R3_SEQNUM>
    </item>
    <item>
     <OBJECT>TABL</OBJECT>
     <OBJ_NAME>ZEBIZ_CHARGESALES_ORDER</OBJ_NAME>
     <OBJECT1>FIEL</OBJECT1>
     <OBJ_NAME1>SHIPPING_ADDRESS</OBJ_NAME1>
     <OBJECT2>FIEL</OBJECT2>
     <OBJ_NAME2>SHIPPING_ADDRESS</OBJ_NAME2>
     <OBJECT_R>TABL</OBJECT_R>
     <OBJ_NAME_R>ZEBIZ_CHARGEADDRESS</OBJ_NAME_R>
     <ID>&lt;element&gt; {http://eBizCharge.ServiceModel.SOAP}ShippingAddress &lt;type&gt; SalesOrder http://eBizCharge.ServiceModel.SOAP http://eBizCharge.ServiceModel.SOAP</ID>
     <IFR_TYPE>element</IFR_TYPE>
     <IFR_NAME>ShippingAddress</IFR_NAME>
     <IFR_TAGTYP>E</IFR_TAGTYP>
     <IFR_MAXOCC>1</IFR_MAXOCC>
     <IFR_OPTNL>X</IFR_OPTNL>
     <IFR_QUALIF>X</IFR_QUALIF>
     <IFR_SCALE>-2</IFR_SCALE>
     <R3_TYPE>FIEL</R3_TYPE>
     <R3_NAME>SHIPPING_ADDRESS</R3_NAME>
     <R3_SEQNUM>000030</R3_SEQNUM>
    </item>
    <item>
     <OBJECT>TABL</OBJECT>
     <OBJ_NAME>ZEBIZ_CHARGESALES_ORDER</OBJ_NAME>
     <OBJECT1>FIEL</OBJECT1>
     <OBJ_NAME1>SHIP_DATE</OBJ_NAME1>
     <OBJECT2>FIEL</OBJECT2>
     <OBJ_NAME2>SHIP_DATE</OBJ_NAME2>
     <ID>&lt;element&gt; {http://eBizCharge.ServiceModel.SOAP}ShipDate &lt;type&gt; SalesOrder http://eBizCharge.ServiceModel.SOAP http://eBizCharge.ServiceModel.SOAP</ID>
     <IFR_TYPE>element</IFR_TYPE>
     <IFR_NAME>ShipDate</IFR_NAME>
     <IFR_TAGTYP>E</IFR_TAGTYP>
     <IFR_MAXOCC>1</IFR_MAXOCC>
     <IFR_OPTNL>X</IFR_OPTNL>
     <IFR_QUALIF>X</IFR_QUALIF>
     <IFR_XSDTYP>string</IFR_XSDTYP>
     <IFR_SCALE>-2</IFR_SCALE>
     <R3_TYPE>FIEL</R3_TYPE>
     <R3_NAME>SHIP_DATE</R3_NAME>
     <R3_DATATYP>STRG</R3_DATATYP>
     <R3_SEQNUM>000033</R3_SEQNUM>
    </item>
    <item>
     <OBJECT>TABL</OBJECT>
     <OBJ_NAME>ZEBIZ_CHARGESALES_ORDER</OBJ_NAME>
     <OBJECT1>FIEL</OBJECT1>
     <OBJ_NAME1>SHIP_VIA</OBJ_NAME1>
     <OBJECT2>FIEL</OBJECT2>
     <OBJ_NAME2>SHIP_VIA</OBJ_NAME2>
     <ID>&lt;element&gt; {http://eBizCharge.ServiceModel.SOAP}ShipVia &lt;type&gt; SalesOrder http://eBizCharge.ServiceModel.SOAP http://eBizCharge.ServiceModel.SOAP</ID>
     <IFR_TYPE>element</IFR_TYPE>
     <IFR_NAME>ShipVia</IFR_NAME>
     <IFR_TAGTYP>E</IFR_TAGTYP>
     <IFR_MAXOCC>1</IFR_MAXOCC>
     <IFR_OPTNL>X</IFR_OPTNL>
     <IFR_QUALIF>X</IFR_QUALIF>
     <IFR_XSDTYP>string</IFR_XSDTYP>
     <IFR_SCALE>-2</IFR_SCALE>
     <R3_TYPE>FIEL</R3_TYPE>
     <R3_NAME>SHIP_VIA</R3_NAME>
     <R3_DATATYP>STRG</R3_DATATYP>
     <R3_SEQNUM>000034</R3_SEQNUM>
    </item>
    <item>
     <OBJECT>TABL</OBJECT>
     <OBJ_NAME>ZEBIZ_CHARGESALES_ORDER</OBJ_NAME>
     <OBJECT1>FIEL</OBJECT1>
     <OBJ_NAME1>SOFTWARE</OBJ_NAME1>
     <OBJECT2>FIEL</OBJECT2>
     <OBJ_NAME2>SOFTWARE</OBJ_NAME2>
     <ID>&lt;element&gt; {http://eBizCharge.ServiceModel.SOAP}Software &lt;type&gt; SalesOrder http://eBizCharge.ServiceModel.SOAP http://eBizCharge.ServiceModel.SOAP</ID>
     <IFR_TYPE>element</IFR_TYPE>
     <IFR_NAME>Software</IFR_NAME>
     <IFR_TAGTYP>E</IFR_TAGTYP>
     <IFR_MAXOCC>1</IFR_MAXOCC>
     <IFR_OPTNL>X</IFR_OPTNL>
     <IFR_QUALIF>X</IFR_QUALIF>
     <IFR_XSDTYP>string</IFR_XSDTYP>
     <IFR_SCALE>-2</IFR_SCALE>
     <R3_TYPE>FIEL</R3_TYPE>
     <R3_NAME>SOFTWARE</R3_NAME>
     <R3_DATATYP>STRG</R3_DATATYP>
     <R3_SEQNUM>000022</R3_SEQNUM>
    </item>
    <item>
     <OBJECT>TABL</OBJECT>
     <OBJ_NAME>ZEBIZ_CHARGESALES_ORDER</OBJ_NAME>
     <OBJECT1>FIEL</OBJECT1>
     <OBJ_NAME1>SUB_CUSTOMER_ID</OBJ_NAME1>
     <OBJECT2>FIEL</OBJECT2>
     <OBJ_NAME2>SUB_CUSTOMER_ID</OBJ_NAME2>
     <ID>&lt;element&gt; {http://eBizCharge.ServiceModel.SOAP}SubCustomerId &lt;type&gt; SalesOrder http://eBizCharge.ServiceModel.SOAP http://eBizCharge.ServiceModel.SOAP</ID>
     <IFR_TYPE>element</IFR_TYPE>
     <IFR_NAME>SubCustomerId</IFR_NAME>
     <IFR_TAGTYP>E</IFR_TAGTYP>
     <IFR_MAXOCC>1</IFR_MAXOCC>
     <IFR_OPTNL>X</IFR_OPTNL>
     <IFR_QUALIF>X</IFR_QUALIF>
     <IFR_XSDTYP>string</IFR_XSDTYP>
     <IFR_SCALE>-2</IFR_SCALE>
     <R3_TYPE>FIEL</R3_TYPE>
     <R3_NAME>SUB_CUSTOMER_ID</R3_NAME>
     <R3_DATATYP>STRG</R3_DATATYP>
     <R3_SEQNUM>000003</R3_SEQNUM>
    </item>
    <item>
     <OBJECT>TABL</OBJECT>
     <OBJ_NAME>ZEBIZ_CHARGESALES_ORDER</OBJ_NAME>
     <OBJECT1>FIEL</OBJECT1>
     <OBJ_NAME1>TERMS_ID</OBJ_NAME1>
     <OBJECT2>FIEL</OBJECT2>
     <OBJ_NAME2>TERMS_ID</OBJ_NAME2>
     <ID>&lt;element&gt; {http://eBizCharge.ServiceModel.SOAP}TermsId &lt;type&gt; SalesOrder http://eBizCharge.ServiceModel.SOAP http://eBizCharge.ServiceModel.SOAP</ID>
     <IFR_TYPE>element</IFR_TYPE>
     <IFR_NAME>TermsId</IFR_NAME>
     <IFR_TAGTYP>E</IFR_TAGTYP>
     <IFR_MAXOCC>1</IFR_MAXOCC>
     <IFR_OPTNL>X</IFR_OPTNL>
     <IFR_QUALIF>X</IFR_QUALIF>
     <IFR_XSDTYP>string</IFR_XSDTYP>
     <IFR_SCALE>-2</IFR_SCALE>
     <R3_TYPE>FIEL</R3_TYPE>
     <R3_NAME>TERMS_ID</R3_NAME>
     <R3_DATATYP>STRG</R3_DATATYP>
     <R3_SEQNUM>000036</R3_SEQNUM>
    </item>
    <item>
     <OBJECT>TABL</OBJECT>
     <OBJ_NAME>ZEBIZ_CHARGESALES_ORDER</OBJ_NAME>
     <OBJECT1>FIEL</OBJECT1>
     <OBJ_NAME1>TOTAL_TAX_AMOUNT</OBJ_NAME1>
     <OBJECT2>FIEL</OBJECT2>
     <OBJ_NAME2>TOTAL_TAX_AMOUNT</OBJ_NAME2>
     <ID>&lt;element&gt; {http://eBizCharge.ServiceModel.SOAP}TotalTaxAmount &lt;type&gt; SalesOrder http://eBizCharge.ServiceModel.SOAP http://eBizCharge.ServiceModel.SOAP</ID>
     <IFR_TYPE>element</IFR_TYPE>
     <IFR_NAME>TotalTaxAmount</IFR_NAME>
     <IFR_TAGTYP>E</IFR_TAGTYP>
     <IFR_MINOCC>1</IFR_MINOCC>
     <IFR_MAXOCC>1</IFR_MAXOCC>
     <IFR_QUALIF>X</IFR_QUALIF>
     <IFR_XSDTYP>decimal</IFR_XSDTYP>
     <IFR_NILLABLE>X</IFR_NILLABLE>
     <IFR_SCALE>-2</IFR_SCALE>
     <R3_TYPE>FIEL</R3_TYPE>
     <R3_NAME>TOTAL_TAX_AMOUNT</R3_NAME>
     <R3_DATATYP>STRG</R3_DATATYP>
     <R3_SEQNUM>000026</R3_SEQNUM>
    </item>
    <item>
     <OBJECT>TABL</OBJECT>
     <OBJ_NAME>ZEBIZ_CHARGESALES_ORDER</OBJ_NAME>
     <OBJECT1>FIEL</OBJECT1>
     <OBJ_NAME1>TYPE_ID</OBJ_NAME1>
     <OBJECT2>FIEL</OBJECT2>
     <OBJ_NAME2>TYPE_ID</OBJ_NAME2>
     <ID>&lt;element&gt; {http://eBizCharge.ServiceModel.SOAP}TypeId &lt;type&gt; SalesOrder http://eBizCharge.ServiceModel.SOAP http://eBizCharge.ServiceModel.SOAP</ID>
     <IFR_TYPE>element</IFR_TYPE>
     <IFR_NAME>TypeId</IFR_NAME>
     <IFR_TAGTYP>E</IFR_TAGTYP>
     <IFR_MAXOCC>1</IFR_MAXOCC>
     <IFR_OPTNL>X</IFR_OPTNL>
     <IFR_QUALIF>X</IFR_QUALIF>
     <IFR_XSDTYP>string</IFR_XSDTYP>
     <IFR_SCALE>-2</IFR_SCALE>
     <R3_TYPE>FIEL</R3_TYPE>
     <R3_NAME>TYPE_ID</R3_NAME>
     <R3_DATATYP>STRG</R3_DATATYP>
     <R3_SEQNUM>000013</R3_SEQNUM>
    </item>
    <item>
     <OBJECT>TABL</OBJECT>
     <OBJ_NAME>ZEBIZ_CHARGESALES_ORDER</OBJ_NAME>
     <OBJECT1>FIEL</OBJECT1>
     <OBJ_NAME1>UNIQUE_ID</OBJ_NAME1>
     <OBJECT2>FIEL</OBJECT2>
     <OBJ_NAME2>UNIQUE_ID</OBJ_NAME2>
     <ID>&lt;element&gt; {http://eBizCharge.ServiceModel.SOAP}UniqueId &lt;type&gt; SalesOrder http://eBizCharge.ServiceModel.SOAP http://eBizCharge.ServiceModel.SOAP</ID>
     <IFR_TYPE>element</IFR_TYPE>
     <IFR_NAME>UniqueId</IFR_NAME>
     <IFR_TAGTYP>E</IFR_TAGTYP>
     <IFR_MAXOCC>1</IFR_MAXOCC>
     <IFR_OPTNL>X</IFR_OPTNL>
     <IFR_QUALIF>X</IFR_QUALIF>
     <IFR_XSDTYP>string</IFR_XSDTYP>
     <IFR_SCALE>-2</IFR_SCALE>
     <R3_TYPE>FIEL</R3_TYPE>
     <R3_NAME>UNIQUE_ID</R3_NAME>
     <R3_DATATYP>STRG</R3_DATATYP>
     <R3_SEQNUM>000027</R3_SEQNUM>
    </item>
    <item>
     <OBJECT>TABL</OBJECT>
     <OBJ_NAME>ZEBIZ_CHARGESALES_ORDER</OBJ_NAME>
     <OBJECT1>FIEL</OBJECT1>
     <OBJ_NAME1>UPDATED_BY</OBJ_NAME1>
     <OBJECT2>FIEL</OBJECT2>
     <OBJ_NAME2>UPDATED_BY</OBJ_NAME2>
     <ID>&lt;element&gt; {http://eBizCharge.ServiceModel.SOAP}UpdatedBy &lt;type&gt; SalesOrder http://eBizCharge.ServiceModel.SOAP http://eBizCharge.ServiceModel.SOAP</ID>
     <IFR_TYPE>element</IFR_TYPE>
     <IFR_NAME>UpdatedBy</IFR_NAME>
     <IFR_TAGTYP>E</IFR_TAGTYP>
     <IFR_MAXOCC>1</IFR_MAXOCC>
     <IFR_OPTNL>X</IFR_OPTNL>
     <IFR_QUALIF>X</IFR_QUALIF>
     <IFR_XSDTYP>string</IFR_XSDTYP>
     <IFR_SCALE>-2</IFR_SCALE>
     <R3_TYPE>FIEL</R3_TYPE>
     <R3_NAME>UPDATED_BY</R3_NAME>
     <R3_DATATYP>STRG</R3_DATATYP>
     <R3_SEQNUM>000015</R3_SEQNUM>
    </item>
    <item>
     <OBJECT>TABL</OBJECT>
     <OBJ_NAME>ZEBIZ_CHARGESALES_ORDER</OBJ_NAME>
     <OBJECT1>FIEL</OBJECT1>
     <OBJ_NAME1>UPLOADED_BY</OBJ_NAME1>
     <OBJECT2>FIEL</OBJECT2>
     <OBJ_NAME2>UPLOADED_BY</OBJ_NAME2>
     <ID>&lt;element&gt; {http://eBizCharge.ServiceModel.SOAP}UploadedBy &lt;type&gt; SalesOrder http://eBizCharge.ServiceModel.SOAP http://eBizCharge.ServiceModel.SOAP</ID>
     <IFR_TYPE>element</IFR_TYPE>
     <IFR_NAME>UploadedBy</IFR_NAME>
     <IFR_TAGTYP>E</IFR_TAGTYP>
     <IFR_MAXOCC>1</IFR_MAXOCC>
     <IFR_OPTNL>X</IFR_OPTNL>
     <IFR_QUALIF>X</IFR_QUALIF>
     <IFR_XSDTYP>string</IFR_XSDTYP>
     <IFR_SCALE>-2</IFR_SCALE>
     <R3_TYPE>FIEL</R3_TYPE>
     <R3_NAME>UPLOADED_BY</R3_NAME>
     <R3_DATATYP>STRG</R3_DATATYP>
     <R3_SEQNUM>000014</R3_SEQNUM>
    </item>
    <item>
     <OBJECT>TABL</OBJECT>
     <OBJ_NAME>ZEBIZ_CHARGESALES_ORDER</OBJ_NAME>
     <OBJECT1>FIEL</OBJECT1>
     <OBJ_NAME1>URL</OBJ_NAME1>
     <OBJECT2>FIEL</OBJECT2>
     <OBJ_NAME2>URL</OBJ_NAME2>
     <ID>&lt;element&gt; {http://eBizCharge.ServiceModel.SOAP}URL &lt;type&gt; SalesOrder http://eBizCharge.ServiceModel.SOAP http://eBizCharge.ServiceModel.SOAP</ID>
     <IFR_TYPE>element</IFR_TYPE>
     <IFR_NAME>URL</IFR_NAME>
     <IFR_TAGTYP>E</IFR_TAGTYP>
     <IFR_MAXOCC>1</IFR_MAXOCC>
     <IFR_OPTNL>X</IFR_OPTNL>
     <IFR_QUALIF>X</IFR_QUALIF>
     <IFR_XSDTYP>string</IFR_XSDTYP>
     <IFR_SCALE>-2</IFR_SCALE>
     <R3_TYPE>FIEL</R3_TYPE>
     <R3_NAME>URL</R3_NAME>
     <R3_DATATYP>STRG</R3_DATATYP>
     <R3_SEQNUM>000025</R3_SEQNUM>
    </item>
    <item>
     <OBJECT>TABL</OBJECT>
     <OBJ_NAME>ZEBIZ_CHARGESALES_ORDER</OBJ_NAME>
     <OBJECT1>TABL</OBJECT1>
     <OBJ_NAME1>ZEBIZ_CHARGESALES_ORDER</OBJ_NAME1>
     <OBJECT2>TABL</OBJECT2>
     <OBJ_NAME2>ZEBIZ_CHARGESALES_ORDER</OBJ_NAME2>
     <ID>&lt;type&gt; SalesOrder http://eBizCharge.ServiceModel.SOAP http://eBizCharge.ServiceModel.SOAP</ID>
     <IFR_TYPE>type</IFR_TYPE>
     <IFR_NAME>SalesOrder</IFR_NAME>
     <IFR_SCALE>-2</IFR_SCALE>
     <R3_TYPE>TABL</R3_TYPE>
     <R3_NAME>ZEBIZ_CHARGESALES_ORDER</R3_NAME>
     <R3_TEXT>Proxy Structure (generated)</R3_TEXT>
     <CATEGORY>ifmtypedef</CATEGORY>
    </item>
   </PROXY_DATA>
  </asx:values>
 </asx:abap>
</abapGit>
